django_userena-2.0.1.dist-info/DESCRIPTION.rst
django_userena-2.0.1.dist-info/METADATA
django_userena-2.0.1.dist-info/RECORD
django_userena-2.0.1.dist-info/WHEEL
django_userena-2.0.1.dist-info/metadata.json
django_userena-2.0.1.dist-info/top_level.txt
userena/__init__.py
userena/admin.py
userena/apps.py
userena/backends.py
userena/compat.py
userena/decorators.py
userena/forms.py
userena/mail.py
userena/managers.py
userena/middleware.py
userena/models.py
userena/settings.py
userena/signals.py
userena/urls.py
userena/utils.py
userena/views.py
userena/contrib/__init__.py
userena/contrib/umessages/__init__.py
userena/contrib/umessages/admin.py
userena/contrib/umessages/fields.py
userena/contrib/umessages/forms.py
userena/contrib/umessages/managers.py
userena/contrib/umessages/models.py
userena/contrib/umessages/signals.py
userena/contrib/umessages/urls.py
userena/contrib/umessages/views.py
userena/contrib/umessages/fixtures/messages.json
userena/contrib/umessages/migrations/0001_initial.py
userena/contrib/umessages/migrations/__init__.py
userena/contrib/umessages/south_migrations/0001_initial.py
userena/contrib/umessages/south_migrations/__init__.py
userena/contrib/umessages/templates/base.html
userena/contrib/umessages/templates/umessages/base_message.html
userena/contrib/umessages/templates/umessages/message_detail.html
userena/contrib/umessages/templates/umessages/message_form.html
userena/contrib/umessages/templates/umessages/message_list.html
userena/contrib/umessages/templatetags/__init__.py
userena/contrib/umessages/templatetags/umessages_tags.py
userena/contrib/umessages/tests/__init__.py
userena/contrib/umessages/tests/test_fields.py
userena/contrib/umessages/tests/test_forms.py
userena/contrib/umessages/tests/test_managers.py
userena/contrib/umessages/tests/test_models.py
userena/contrib/umessages/tests/test_views.py
userena/fixtures/profiles.json
userena/fixtures/users.json
userena/locale/bg/LC_MESSAGES/django.mo
userena/locale/bg/LC_MESSAGES/django.po
userena/locale/de/LC_MESSAGES/django.mo
userena/locale/de/LC_MESSAGES/django.po
userena/locale/de_du/LC_MESSAGES/django.mo
userena/locale/de_du/LC_MESSAGES/django.po
